vintasend_flask_mail/__init__.py
vintasend_flask_mail/py.typed
vintasend_flask_mail/services/__init__.py
vintasend_flask_mail/services/notification_adapters/__init__.py
vintasend_flask_mail/services/notification_adapters/flask_mail.py
vintasend_flask_mail/services/tests/__init__.py
vintasend_flask_mail/services/tests/test_adapters.py
vintasend_flask_mail-0.1.4.dist-info/LICENSE.txt
vintasend_flask_mail-0.1.4.dist-info/METADATA
vintasend_flask_mail-0.1.4.dist-info/WHEEL
vintasend_flask_mail-0.1.4.dist-info/RECORD
