Metadata-Version: 2.3
Name: vintasend-flask-mail
Version: 0.1.4
Summary: Flask Mail adapter for VintaSend
License: MIT
Author: Hugo bessa
Author-email: hugo@vinta.com.br
Requires-Python: >=3.10,<3.14
Classifier: License :: OSI Approved :: MIT License
Classifier: Programming Language :: Python :: 3
Classifier: Programming Language :: Python :: 3.10
Classifier: Programming Language :: Python :: 3.11
Classifier: Programming Language :: Python :: 3.12
Classifier: Programming Language :: Python :: 3.13
Requires-Dist: flask-mail (>=0.10.0,<0.11.0)
Requires-Dist: vintasend (==0.1.4)
